{
	"configurations" : 
	[
		{
			"directories" : 
			[
				{
					"build" : ".",
					"jsonFile" : "directory-.-Debug-d0094a50bb2071803777.json",
					"minimumCMakeVersion" : 
					{
						"string" : "3.29"
					},
					"projectIndex" : 0,
					"source" : ".",
					"targetIndexes" : 
					[
						0
					]
				}
			],
			"name" : "Debug",
			"projects" : 
			[
				{
					"directoryIndexes" : 
					[
						0
					],
					"name" : "Rojo_Negro",
					"targetIndexes" : 
					[
						0
					]
				}
			],
			"targets" : 
			[
				{
					"directoryIndex" : 0,
					"id" : "Rojo_Negro::@6890427a1f51a3e7e1df",
					"jsonFile" : "target-Rojo_Negro-Debug-2d70bac6482b92d09215.json",
					"name" : "Rojo_Negro",
					"projectIndex" : 0
				}
			]
		}
	],
	"kind" : "codemodel",
	"paths" : 
	{
		"build" : "E:/UNIVERSIDAD/III Semestre/Rojo_Negro/cmake-build-debug",
		"source" : "E:/UNIVERSIDAD/III Semestre/Rojo_Negro"
	},
	"version" : 
	{
		"major" : 2,
		"minor" : 7
	}
}
